stamper/__init__.py
stamper/cli.py
stamper/config.py
stamper/filters.py
stamper/http.py
stamper/stamper.py
stamper-0.1.1.data/scripts/stamp
stamper-0.1.1.data/scripts/stamp2json
stamper-0.1.1.data/scripts/stamps
stamper-0.1.1.data/scripts/time_sum
stamper-0.1.1.dist-info/AUTHORS
stamper-0.1.1.dist-info/LICENSE
stamper-0.1.1.dist-info/METADATA
stamper-0.1.1.dist-info/WHEEL
stamper-0.1.1.dist-info/top_level.txt
stamper-0.1.1.dist-info/RECORD
