Metadata-Version: 2.1
Name: stamper
Version: 0.1.1
Summary: Time tracking tool
Home-page: https://code.codigo23.net/trac/wiki/stamper
Author: Francisco de Borja Lopez Rio
Author-email: borja@codigo23.net
License: BSD licence, see LICENSE
Download-URL: http://pypi.python.org/pypi/stamper#downloads
Platform: UNKNOWN
Classifier: Development Status :: 4 - Beta
Classifier: Environment :: Console
Classifier: Intended Audience :: End Users/Desktop
Classifier: License :: OSI Approved :: BSD License
Classifier: Natural Language :: English
Classifier: Operating System :: OS Independent
Classifier: Programming Language :: Python :: 3
Classifier: Topic :: Office/Business
Classifier: Topic :: Office/Business :: Scheduling
Classifier: Topic :: Utilities
Requires-Dist: pygal
